biperscan/lenses.py
biperscan/api.py
biperscan/_impl.cpython-312-x86_64-linux-gnu.so
biperscan/plots.py
biperscan/__init__.py
biperscan/_impl.pyx
biperscan/_impl.pxd
biperscan/tests/test_biperscan.py
biperscan/tests/__init__.py
biperscan/cpp/biperscan.h
biperscan/cpp/py_biperscan.h
biperscan/cpp/lib/concepts.h
biperscan/cpp/lib/ostream.cpp
biperscan/cpp/lib/bigrade_ordering.h
biperscan/cpp/lib/linkage_hierarchy.h
biperscan/cpp/lib/graded_matrix.h
biperscan/cpp/lib/minimal_presentation.h
biperscan/cpp/lib/minimal_presentation_graph.h
biperscan/cpp/lib/ostream.h
biperscan/cpp/lib/algorithm.h
biperscan/cpp/lib/minimal_presentation_merges.h
biperscan/cpp/lib/minimal_presentation_iteration_state.h
biperscan/cpp/lib/base_types.h
biperscan-0.1.0.dist-info/WHEEL
biperscan-0.1.0.dist-info/RECORD
biperscan-0.1.0.dist-info/top_level.txt
biperscan-0.1.0.dist-info/METADATA
biperscan-0.1.0.dist-info/licenses/LICENSE
